cloudview/__init__.py
cloudview/azure.py
cloudview/cloudview.py
cloudview/ec2.py
cloudview/gce.py
cloudview/instance.py
cloudview/openstack.py
cloudview/output.py
cloudview/singleton.py
cloudview/templates.py
cloudview/utils.py
cloudview-0.9.data/scripts/cloudview
cloudview-0.9.dist-info/LICENSE
cloudview-0.9.dist-info/METADATA
cloudview-0.9.dist-info/WHEEL
cloudview-0.9.dist-info/top_level.txt
cloudview-0.9.dist-info/RECORD
