Metadata-Version: 2.1
Name: cloudview
Version: 0.9
Summary: View instance information on all supported cloud providers
Home-page: https://github.com/ricardobranco777/cloudview
Author: Ricardo Branco
Author-email: rbranco@suse.de
License: MIT License
Keywords: cloudview
Classifier: Development Status :: 4 - Beta
Classifier: Environment :: Console
Classifier: Intended Audience :: Developers
Classifier: Intended Audience :: System Administrators
Classifier: Topic :: System :: Monitoring
Classifier: License :: OSI Approved :: MIT License
Classifier: Natural Language :: English
Classifier: Operating System :: Unix
Classifier: Programming Language :: Python :: 3.8
Classifier: Programming Language :: Python :: 3.9
Classifier: Programming Language :: Python :: 3.10
Classifier: Programming Language :: Python :: 3.11
Classifier: Programming Language :: Python :: 3 :: Only
Requires-Python: >=3.8
License-File: LICENSE
Requires-Dist: apache-libcloud ==3.8.0
Requires-Dist: cachetools ==5.3.1
Requires-Dist: certifi ==2023.7.22
Requires-Dist: cffi ==1.15.1
Requires-Dist: charset-normalizer ==3.2.0
Requires-Dist: cryptography ==41.0.3
Requires-Dist: hupper ==1.12
Requires-Dist: idna ==3.4
Requires-Dist: Jinja2 ==3.1.2
Requires-Dist: MarkupSafe ==2.1.3
Requires-Dist: PasteDeploy ==3.0.1
Requires-Dist: plaster ==1.1.2
Requires-Dist: plaster-pastedeploy ==1.0.1
Requires-Dist: pycparser ==2.21
Requires-Dist: pyramid ==2.0.1
Requires-Dist: python-dateutil ==2.8.2
Requires-Dist: pytz ==2023.3
Requires-Dist: PyYAML ==6.0.1
Requires-Dist: requests ==2.31.0
Requires-Dist: six ==1.16.0
Requires-Dist: translationstring ==1.4
Requires-Dist: urllib3 ==2.0.4
Requires-Dist: venusian ==3.0.0
Requires-Dist: WebOb ==1.8.7
Requires-Dist: zope.deprecation ==5.0
Requires-Dist: zope.interface ==6.0
